koolbox/__init__.py
koolbox/koolbox.py
koolbox/bin/koolbox
pykoolboxcli-0.3.19.dist-info/METADATA
pykoolboxcli-0.3.19.dist-info/WHEEL
pykoolboxcli-0.3.19.dist-info/entry_points.txt
pykoolboxcli-0.3.19.dist-info/top_level.txt
pykoolboxcli-0.3.19.dist-info/RECORD
