Metadata-Version: 2.4
Name: pykoolboxcli
Version: 0.3.19
Summary: An advanced entrypoint. It contains various tools helping set up environment and run tasks
Author-email: Klim Naidenov <knaydenov@yandex.ru>
Project-URL: Homepage, https://git@git.sourcecraft.dev/0x4b4c494d/pykoolbox.git
Project-URL: Issues, https://sourcecraft.dev/0x4b4c494d/pykoolbox/issues
Classifier: Operating System :: OS Independent
Requires-Python: >=3.0
